[
  {
    "english": "coursed",
    "mandarin": "流动"
  },
  {
    "english": "uttered",
    "mandarin": "发出"
  },
  {
    "english": "wander off",
    "mandarin": "闲逛"
  },
  {
    "english": "aviaries",
    "mandarin": "鸟舍"
  },
  {
    "english": "premises",
    "mandarin": "地点"
  },
  {
    "english": "bulky",
    "mandarin": "笨重的"
  },
  {
    "english": "storks",
    "mandarin": "鹳"
  },
  {
    "english": "pheasants",
    "mandarin": "雉"
  },
  {
    "english": "altar",
    "mandarin": "祭坛"
  }
]